{
    "base": "15 + 1/11",
    "bitwidth": 32,
    "carry_chains": "default",
    "coef_div_modulus": "2",
    "compiler": "gcc -march=native -mtune=native -std=gnu11 -O3 -flto -fomit-frame-pointer -fwrapv -Wno-attributes -Dlimb_weight_gaps_array='{16,15,15,15,15,15,15,15,15,15,15}' -Dq_mpz='(1_mpz<<166) - 5' -Dlimb_t=uint32_t -Dmodulus_bytes_val='21' -Dmodulus_limbs='11' -Da_minus_two_over_four_array='{0x00,0x00,0x00,0x00,0x00,0x00,0x00,0x00,0x00,0x00,0x00,0x00,0x00,0x00,0x00,0x00,0x00,0x00,0x00,0x30,0x39}' -Dmodulus_array='{0x3f,0xff,0xff,0xff,0xff,0xff,0xff,0xff,0xff,0xff,0xff,0xff,0xff,0xff,0xff,0xff,0xff,0xff,0xff,0xff,0xfb}'",
    "compilerxx": "g++ -march=native -mtune=native -std=gnu++11 -O3 -flto -fomit-frame-pointer -fwrapv -Wno-attributes -Dlimb_weight_gaps_array='{16,15,15,15,15,15,15,15,15,15,15}' -Dq_mpz='(1_mpz<<166) - 5' -Dlimb_t=uint32_t -Dmodulus_bytes_val='21' -Dmodulus_limbs='11' -Da_minus_two_over_four_array='{0x00,0x00,0x00,0x00,0x00,0x00,0x00,0x00,0x00,0x00,0x00,0x00,0x00,0x00,0x00,0x00,0x00,0x00,0x00,0x30,0x39}' -Dmodulus_array='{0x3f,0xff,0xff,0xff,0xff,0xff,0xff,0xff,0xff,0xff,0xff,0xff,0xff,0xff,0xff,0xff,0xff,0xff,0xff,0xff,0xfb}'",
    "modulus": "2^166 - 5",
    "operations": [
        "femul",
        "feadd",
        "fesub",
        "fesquare",
        "freeze"
    ],
    "sz": "11"
}
