{
    "base": "38.4",
    "bitwidth": 64,
    "carry_chains": [
        [
            2,
            1,
            9,
            9
        ],
        [
            3,
            2,
            0,
            4,
            1,
            5,
            6,
            7,
            8,
            9
        ],
        [
            3,
            2,
            0,
            0
        ]
    ],
    "coef_div_modulus": "2",
    "compiler": "clang -fbracket-depth=999999 -march=native -mtune=native -std=gnu11 -O3 -flto -fuse-ld=lld -fomit-frame-pointer -fwrapv -Wno-attributes -fno-strict-aliasing -Da24_hex='0x3039' -Da24_val='12345' -Da_minus_two_over_four_array='{0x00,0x00,0x00,0x00,0x00,0x00,0x00,0x00,0x00,0x00,0x00,0x00,0x00,0x00,0x00,0x00,0x00,0x00,0x00,0x00,0x00,0x00,0x00,0x00,0x00,0x00,0x00,0x00,0x00,0x00,0x00,0x00,0x00,0x00,0x00,0x00,0x00,0x00,0x00,0x00,0x00,0x00,0x00,0x00,0x00,0x00,0x30,0x39}' -Dbitwidth='64' -Dlimb_weight_gaps_array='{39,38,39,38,38,39,38,39,38,38}' -Dmodulus_array='{0xff,0xff,0xff,0xff,0xff,0xff,0xff,0xff,0xff,0xff,0xff,0xff,0xff,0xff,0xff,0xff,0xff,0xff,0xff,0xff,0xff,0xff,0xff,0xff,0xff,0xff,0xff,0xff,0xff,0xff,0xff,0xfe,0xff,0xff,0xff,0xff,0x00,0x00,0x00,0x00,0x00,0x00,0x00,0x00,0xff,0xff,0xff,0xff}' -Dmodulus_bytes_val='48' -Dmodulus_limbs='10' -Dq_mpz='(1_mpz<<384) - (1_mpz<<128) - (1_mpz<<96) + (1_mpz<<32) - 1'",
    "compilerxx": "clang++ -fbracket-depth=999999 -march=native -mtune=native -std=gnu++11 -O3 -flto -fuse-ld=lld -fomit-frame-pointer -fwrapv -Wno-attributes -fno-strict-aliasing -Da24_hex='0x3039' -Da24_val='12345' -Da_minus_two_over_four_array='{0x00,0x00,0x00,0x00,0x00,0x00,0x00,0x00,0x00,0x00,0x00,0x00,0x00,0x00,0x00,0x00,0x00,0x00,0x00,0x00,0x00,0x00,0x00,0x00,0x00,0x00,0x00,0x00,0x00,0x00,0x00,0x00,0x00,0x00,0x00,0x00,0x00,0x00,0x00,0x00,0x00,0x00,0x00,0x00,0x00,0x00,0x30,0x39}' -Dbitwidth='64' -Dlimb_weight_gaps_array='{39,38,39,38,38,39,38,39,38,38}' -Dmodulus_array='{0xff,0xff,0xff,0xff,0xff,0xff,0xff,0xff,0xff,0xff,0xff,0xff,0xff,0xff,0xff,0xff,0xff,0xff,0xff,0xff,0xff,0xff,0xff,0xff,0xff,0xff,0xff,0xff,0xff,0xff,0xff,0xfe,0xff,0xff,0xff,0xff,0x00,0x00,0x00,0x00,0x00,0x00,0x00,0x00,0xff,0xff,0xff,0xff}' -Dmodulus_bytes_val='48' -Dmodulus_limbs='10' -Dq_mpz='(1_mpz<<384) - (1_mpz<<128) - (1_mpz<<96) + (1_mpz<<32) - 1'",
    "modulus": "2^384 - 2^128 - 2^96 + 2^32 - 1",
    "operations": [
        "femul",
        "feadd",
        "fesub",
        "fesquare",
        "fecarry",
        "freeze"
    ],
    "sz": "10"
}
